evoclusterstream/__init__.py
evoclusterstream/cluster/EvoDBSCAN.py
evoclusterstream/cluster/EvoLouvain.py
evoclusterstream/cluster/__init__.py
evoclusterstream/stream/TweepyStreamer.py
evoclusterstream/stream/__init__.py
evoclusterstream/stream/data/uscities.csv
evoclusterstream-2.0.0.dist-info/LICENSE
evoclusterstream-2.0.0.dist-info/METADATA
evoclusterstream-2.0.0.dist-info/WHEEL
evoclusterstream-2.0.0.dist-info/top_level.txt
evoclusterstream-2.0.0.dist-info/RECORD
